udspy/__init__.py
udspy/adapter.py
udspy/callback.py
udspy/confirmation.py
udspy/decorators.py
udspy/exceptions.py
udspy/formatters.py
udspy/history.py
udspy/settings.py
udspy/signature.py
udspy/streaming.py
udspy/lm/__init__.py
udspy/lm/base.py
udspy/lm/factory.py
udspy/lm/openai.py
udspy/lm/types.py
udspy/module/__init__.py
udspy/module/base.py
udspy/module/callbacks.py
udspy/module/chain_of_thought.py
udspy/module/predict.py
udspy/module/react.py
udspy/tool/__init__.py
udspy/tool/decorator.py
udspy/tool/tool.py
udspy/tool/types.py
udspy/utils/__init__.py
udspy/utils/async_support.py
udspy/utils/formatting.py
udspy/utils/schema.py
udspy-0.1.6.dist-info/METADATA
udspy-0.1.6.dist-info/WHEEL
udspy-0.1.6.dist-info/licenses/LICENSE
udspy-0.1.6.dist-info/RECORD
